circle_fitting_3d/__init__.py
circle_fitting_3d/circle_3d.py
circle_fitting_3d-1.0.0.dist-info/LICENSE
circle_fitting_3d-1.0.0.dist-info/METADATA
circle_fitting_3d-1.0.0.dist-info/WHEEL
circle_fitting_3d-1.0.0.dist-info/top_level.txt
circle_fitting_3d-1.0.0.dist-info/RECORD
