Metadata-Version: 2.1
Name: circle-fitting-3d
Version: 1.0.0
Summary: This package allows to compute the best fit circle given points in three-dimensional space.
Author-email: Cristiano Pizzamiglio <cristianopizzamiglio@gmail.com>
License:         
Project-URL: Homepage, https://github.com/CristianoPizzamiglio/circle-fitting-3d
Keywords: circle,best-fit,3D
Classifier: Programming Language :: Python :: 3
Classifier: License :: OSI Approved :: BSD License
Classifier: Operating System :: OS Independent
Requires-Python: >=3.7
License-File: LICENSE
Requires-Dist: scikit-spatial (>=1.0.1)
